mcp_server_undetected_chromedriver/__init__.py
mcp_server_undetected_chromedriver/server.py
mseep_mcp_server_undetected_chromedriver-0.1.2.dist-info/METADATA
mseep_mcp_server_undetected_chromedriver-0.1.2.dist-info/WHEEL
mseep_mcp_server_undetected_chromedriver-0.1.2.dist-info/entry_points.txt
mseep_mcp_server_undetected_chromedriver-0.1.2.dist-info/licenses/LICENSE
mseep_mcp_server_undetected_chromedriver-0.1.2.dist-info/RECORD
